ginza/__init__.py
ginza/__main__.py
ginza/analyzer.py
ginza/bunsetu_recognizer.py
ginza/command_line.py
ginza/compound_splitter.py
ginza/disable_sentencizer.py
ginza/ene_ontonotes_mapper.py
ginza-5.2.0.dist-info/LICENSE
ginza-5.2.0.dist-info/METADATA
ginza-5.2.0.dist-info/WHEEL
ginza-5.2.0.dist-info/entry_points.txt
ginza-5.2.0.dist-info/top_level.txt
ginza-5.2.0.dist-info/RECORD
