Metadata-Version: 2.1
Name: ginza
Version: 5.2.0
Summary: GiNZA, An Open Source Japanese NLP Library, based on Universal Dependencies
Home-page: https://github.com/megagonlabs/ginza
Author: Megagon Labs, Tokyo.
Author-email: ginza@megagon.ai
License: MIT
Requires-Python: >=3.8
License-File: LICENSE
